MANIFEST.in
README.rst
setup.py
cliez/__init__.py
cliez/component.py
cliez/main.py
cliez/mixins.py
cliez/parser.py
cliez/slot.py
cliez/utils.py
cliez.egg-info/PKG-INFO
cliez.egg-info/SOURCES.txt
cliez.egg-info/dependency_links.txt
cliez.egg-info/entry_points.txt
cliez.egg-info/not-zip-safe
cliez.egg-info/requires.txt
cliez.egg-info/top_level.txt
cliez/components/__init__.py
cliez/components/check.py
cliez/components/create.py
cliez/components/init.py
cliez/conf/__init__.py
tests/res_settings/__init__.py
tests/res_settings/demo.py
tests/test_components/__init__.py
tests/test_components/create.py
tests/test_components/init.py