Metadata-Version: 1.1
Name: cliez
Version: 2.1.0
Summary: make CLI-App easier
Home-page: https://github.com/wangwenpei/cliez
Author: WANG WENPEI
Author-email: wangwenpei@nextoa.com
License: MIT
Download-URL: https://github.com/wangwenpei/cliez/tarball/master
Keywords: cli
Platform: UNKNOWN
